defensive_pandas_merge/__init__.py
defensive_pandas_merge/merge_inspector.py
defensive_pandas_merge-0.2.dist-info/LICENSE.txt
defensive_pandas_merge-0.2.dist-info/METADATA
defensive_pandas_merge-0.2.dist-info/WHEEL
defensive_pandas_merge-0.2.dist-info/top_level.txt
defensive_pandas_merge-0.2.dist-info/RECORD
